[
  {
    "source": "teacher",
    "teacher_file": "d:/Study/Programming/operations/Operation1/data_100200400.xlsx",
    "model": "a",
    "run_maat": true,
    "seed": 42,
    "exact_time_limit": 1800.0,
    "exact_mip_gap": 0.0001,
    "maat_iterations": 10,
    "maat_beta": 1.5,
    "maat_aggregated_time_limit": 150.0,
    "maat_aggregated_mip_gap": 0.005,
    "maat_final_time_limit": 108.0,
    "maat_gamma": 2.5,
    "output_name": "teacher_data_100200400_model_a_maat.json"
  },
  {
    "source": "teacher",
    "teacher_file": "d:/Study/Programming/operations/Operation1/data_200400800.xlsx",
    "model": "a",
    "run_maat": true,
    "seed": 42,
    "exact_time_limit": 3600.0,
    "exact_mip_gap": 0.0001,
    "maat_iterations": 10,
    "maat_beta": 1.5,
    "maat_aggregated_time_limit": 150.0,
    "maat_aggregated_mip_gap": 0.005,
    "maat_final_time_limit": 108.0,
    "maat_gamma": 2.5,
    "output_name": "teacher_data_200400800_model_a_maat.json"
  },
  {
    "source": "teacher",
    "teacher_file": "d:/Study/Programming/operations/Operation1/data_100200400.xlsx",
    "model": "b",
    "run_maat": true,
    "seed": 42,
    "exact_time_limit": 1800.0,
    "exact_mip_gap": 0.0001,
    "maat_iterations": 10,
    "maat_beta": 3.0,
    "maat_aggregated_time_limit": 150.0,
    "maat_aggregated_mip_gap": 0.005,
    "maat_final_time_limit": 108.0,
    "maat_gamma": 2.5,
    "output_name": "teacher_data_100200400_model_b_maat.json"
  },
  {
    "source": "teacher",
    "teacher_file": "d:/Study/Programming/operations/Operation1/data_200400800.xlsx",
    "model": "b",
    "run_maat": true,
    "seed": 42,
    "exact_time_limit": 3600.0,
    "exact_mip_gap": 0.0001,
    "maat_iterations": 10,
    "maat_beta": 3.0,
    "maat_aggregated_time_limit": 150.0,
    "maat_aggregated_mip_gap": 0.005,
    "maat_final_time_limit": 108.0,
    "maat_gamma": 2.5,
    "output_name": "teacher_data_200400800_model_b_maat.json"
  },
  {
    "source": "random",
    "model": "a",
    "run_maat": true,
    "seed": 42,
    "plants": 5,
    "depots": 20,
    "customers": 40,
    "products": 5,
    "exact_time_limit": 300.0,
    "maat_iterations": 10,
    "output_name": "random_l5_m20_n40_p5_model_a_maat.json"
  },
  {
    "source": "random",
    "model": "a",
    "run_maat": true,
    "seed": 43,
    "plants": 8,
    "depots": 30,
    "customers": 60,
    "products": 5,
    "exact_time_limit": 300.0,
    "maat_iterations": 10,
    "output_name": "random_l8_m30_n60_p5_model_a_maat.json"
  }
]
